aiomysql/.gitignore
aiomysql/__init__.py
aiomysql/_scm_version.py
aiomysql/_scm_version.pyi
aiomysql/_version.py
aiomysql/connection.py
aiomysql/cursors.py
aiomysql/log.py
aiomysql/pool.py
aiomysql/utils.py
aiomysql/sa/__init__.py
aiomysql/sa/connection.py
aiomysql/sa/engine.py
aiomysql/sa/exc.py
aiomysql/sa/result.py
aiomysql/sa/transaction.py
aiomysql-0.3.1.dist-info/licenses/LICENSE
docs/Makefile
docs/conf.py
docs/connection.rst
docs/contributing.rst
docs/cursors.rst
docs/examples.rst
docs/glossary.rst
docs/index.rst
docs/make.bat
docs/pool.rst
docs/sa.rst
docs/tutorial.rst
examples/example.py
examples/example_callproc.py
examples/example_callproc_oldstyle.py
examples/example_cursors.py
examples/example_executemany.py
examples/example_executemany_oldstyle.py
examples/example_oldstyle.py
examples/example_pool.py
examples/example_pool_oldstyle.py
examples/example_simple_sa.py
examples/example_simple_sa_oldstyle.py
examples/example_ssl.py
examples/example_transaction.py
examples/example_transaction_oldstyle.py
aiomysql-0.3.1.dist-info/METADATA
aiomysql-0.3.1.dist-info/WHEEL
aiomysql-0.3.1.dist-info/top_level.txt
aiomysql-0.3.1.dist-info/RECORD
