Metadata-Version: 2.4
Name: aiomysql
Version: 0.3.1
Summary: MySQL driver for asyncio.
Author-email: Nikolay Novik <nickolainovik@gmail.com>
License-Expression: MIT
Project-URL: homepage, https://github.com/aio-libs/aiomysql
Project-URL: source, https://github.com/aio-libs/aiomysql
Project-URL: download, https://pypi.python.org/pypi/aiomysql
Project-URL: changelog, https://github.com/aio-libs/aiomysql/blob/main/CHANGES.txt
Project-URL: documentation, https://aiomysql.readthedocs.io/
Project-URL: issues, https://github.com/aio-libs/aiomysql/issues
Project-URL: GitHub: CI, https://github.com/aio-libs/aiomysql/actions
Project-URL: GitHub: discussions, https://github.com/aio-libs/aiomysql/discussions
Keywords: mysql,mariadb,asyncio,aiomysql
Platform: POSIX
Classifier: Intended Audience :: Developers
Classifier: Programming Language :: Python :: 3
Classifier: Programming Language :: Python :: 3.9
Classifier: Programming Language :: Python :: 3.10
Classifier: Programming Language :: Python :: 3.11
Classifier: Programming Language :: Python :: 3.12
Classifier: Programming Language :: Python :: 3.13
Classifier: Operating System :: POSIX
Classifier: Environment :: Web Environment
Classifier: Development Status :: 3 - Alpha
Classifier: Topic :: Database
Classifier: Topic :: Database :: Front-Ends
Classifier: Framework :: AsyncIO
Requires-Python: >=3.9
License-File: LICENSE
Requires-Dist: PyMySQL>=1.0
Provides-Extra: sa
Requires-Dist: sqlalchemy<1.4,>=1.3; extra == "sa"
Provides-Extra: rsa
Requires-Dist: PyMySQL[rsa]>=1.0; extra == "rsa"
Dynamic: license-file
